sahi_processor/__init__.py
sahi_processor/sahi_processor.py
sahi_processor/utils/__init__.py
sahi_processor/utils/misc.py
sahi_processor-0.0.4.dist-info/LICENSE
sahi_processor-0.0.4.dist-info/METADATA
sahi_processor-0.0.4.dist-info/WHEEL
sahi_processor-0.0.4.dist-info/top_level.txt
sahi_processor-0.0.4.dist-info/RECORD
