Metadata-Version: 2.1
Name: sahi_processor
Version: 0.0.4
Summary: Using SAHI as a pre and post processing step
Author: Ernest Lim
Project-URL: Homepage, https://github.com/ernestlwt/sahi_processor
Project-URL: Issues, https://github.com/ernestlwt/sahi_processor/issues
Classifier: Programming Language :: Python :: 3
Classifier: License :: OSI Approved :: MIT License
Classifier: Operating System :: OS Independent
Requires-Python: >=3.8
License-File: LICENSE
Requires-Dist: sahi >=0.11.10
